{
  "note_id": "6a22183c000000002202364e",
  "canonical_url": "https://www.xiaohongshu.com/explore/6a22183c000000002202364e",
  "creator_name": "曲琪小饼干儿🍪",
  "creator_profile_url": "https://www.xiaohongshu.com/user/profile/5ce2345400000000180188d5",
  "title": "今日早餐🥣酸汤麻酱面➕虾饺➕小烤肠",
  "publish_time": "2026-06-05T00:28:44+00:00",
  "duration_seconds": 71.7,
  "note_type": "video",
  "selection_reason": "搜索「早餐vlog」第 4 条候选；type=video；时长 71.7s 在 30—120s 内；180 天内发布；非品牌官方号；标题命中食品生活场景；无排除信号。口播/字幕与场景段落数以实际转写和抽帧分析为准。",
  "usage_scope": "stage_2_representative_poc",
  "human_verified": false,
  "observed_at": "2026-07-18T14:01:32.711579+00:00",
  "source": "page_observed"
}